addrext/__init__.py
addrext/addrext.py
addrext/phrase_entity_encoder.py
addrext/data/address/_corner_cases.csv
addrext/data/address/address.csv
addrext/data/address/apts.csv
addrext/data/address/arti.csv
addrext/data/address/attn.csv
addrext/data/address/common_street.csv
addrext/data/address/conjs.csv
addrext/data/address/deleg.csv
addrext/data/address/dir.csv
addrext/data/address/dirs.csv
addrext/data/address/gfeatures.csv
addrext/data/address/keep.csv
addrext/data/address/negatives.csv
addrext/data/address/nths.csv
addrext/data/address/numbers.csv
addrext/data/address/pobox.csv
addrext/data/address/pre.csv
addrext/data/address/preps.csv
addrext/data/address/sp_arti.csv
addrext/data/address/sp_pre.csv
addrext/data/address/sp_way.csv
addrext/data/address/structures.csv
addrext/data/address/suite.csv
addrext/data/address/ways.csv
addrext/data/address/wordways.csv
addrext/data/address/xxxxx.csv
addrext-0.0.6.dist-info/DESCRIPTION.rst
addrext-0.0.6.dist-info/METADATA
addrext-0.0.6.dist-info/RECORD
addrext-0.0.6.dist-info/WHEEL
addrext-0.0.6.dist-info/metadata.json
addrext-0.0.6.dist-info/top_level.txt
