Metadata-Version: 2.0
Name: addrext
Version: 0.0.6
Summary: Address Extractor
Home-page: https://github.com/hydraseq/addrext
Author: Efrain Olivares
Author-email: efrain.olivares@gmail.com
License: MIT
Platform: UNKNOWN
Requires-Dist: hydraseq
